osrm/__init__.py
osrm/engine/__init__.py
osrm/engine/api/__init__.py
osrm/engine/api/fbresult/Annotation.py
osrm/engine/api/fbresult/Error.py
osrm/engine/api/fbresult/FBResult.py
osrm/engine/api/fbresult/Intersection.py
osrm/engine/api/fbresult/Lane.py
osrm/engine/api/fbresult/Leg.py
osrm/engine/api/fbresult/ManeuverType.py
osrm/engine/api/fbresult/Metadata.py
osrm/engine/api/fbresult/Position.py
osrm/engine/api/fbresult/RouteObject.py
osrm/engine/api/fbresult/Step.py
osrm/engine/api/fbresult/StepManeuver.py
osrm/engine/api/fbresult/Table.py
osrm/engine/api/fbresult/Turn.py
osrm/engine/api/fbresult/Uint64Pair.py
osrm/engine/api/fbresult/Waypoint.py
osrm/engine/api/fbresult/__init__.py
osrmfb-0.1.0.dist-info/LICENSE
osrmfb-0.1.0.dist-info/METADATA
osrmfb-0.1.0.dist-info/WHEEL
osrmfb-0.1.0.dist-info/top_level.txt
osrmfb-0.1.0.dist-info/RECORD
