Metadata-Version: 2.1
Name: osrmfb
Version: 0.1.0
Summary: osrm flatbuffer def
Home-page: UNKNOWN
Author: chang@nextbillion.ai
Author-email: chang@nextbillion.ai
License: UNKNOWN
Platform: UNKNOWN
Classifier: Programming Language :: Python :: 3
Classifier: License :: OSI Approved :: MIT License
Classifier: Operating System :: OS Independent
Requires-Python: >=3.6
